{
  "swagger": "2.0",
  "info": {
    "version": "1.0.0",
    "title": "REST API",
    "description": ""
  },
  "host": "localhost:3000",
  "basePath": "/",
  "schemes": [
    "http"
  ],
  "paths": {
    "/adverts/{userId}": {
      "get": {
        "description": "",
        "parameters": [
          {
            "name": "userId",
            "in": "path",
            "required": true,
            "type": "string"
          }
        ],
        "responses": {
          "201": {
            "description": "Created"
          }
        }
      }
    },
    "/adverts/": {
      "get": {
        "description": "",
        "parameters": [],
        "responses": {
          "200": {
            "description": "OK"
          }
        }
      },
      "post": {
        "description": "",
        "parameters": [],
        "responses": {
          "201": {
            "description": "Created"
          }
        }
      }
    },
    "/adverts/{id}": {
      "patch": {
        "description": "",
        "parameters": [
          {
            "name": "id",
            "in": "path",
            "required": true,
            "type": "string"
          }
        ],
        "responses": {
          "200": {
            "description": "OK"
          }
        }
      },
      "delete": {
        "description": "",
        "parameters": [
          {
            "name": "id",
            "in": "path",
            "required": true,
            "type": "string"
          }
        ],
        "responses": {
          "202": {
            "description": "Accepted"
          }
        }
      }
    }
  }
}